expyrun/__init__.py
expyrun/config.py
expyrun/main.py
expyrun/py.typed
expyrun-0.2.0.dist-info/LICENSE
expyrun-0.2.0.dist-info/METADATA
expyrun-0.2.0.dist-info/WHEEL
expyrun-0.2.0.dist-info/entry_points.txt
expyrun-0.2.0.dist-info/top_level.txt
expyrun-0.2.0.dist-info/RECORD
