Metadata-Version: 2.1
Name: expyrun
Version: 0.2.0
Summary: Run reproducible experiments from yaml configuration file
Home-page: https://github.com/raphaelreme/expyrun
Author: Raphael Reme
Author-email: raphaelreme-dev@protonmail.com
License: MIT
Keywords: experiments,reproducibility,machine learning
Classifier: Development Status :: 4 - Beta
Classifier: License :: OSI Approved :: MIT License
Classifier: Natural Language :: English
Classifier: Operating System :: OS Independent
Classifier: Programming Language :: Python :: 3.7
Classifier: Programming Language :: Python :: 3.8
Classifier: Programming Language :: Python :: 3.9
Classifier: Programming Language :: Python :: 3.10
Classifier: Programming Language :: Python :: 3.11
Classifier: Programming Language :: Python :: 3.12
Requires-Python: >=3.7
License-File: LICENSE
Requires-Dist: pyyaml
